Metadata-Version: 1.1
Name: wildqat
Version: 1.1.1
Summary: Python Framework for Ising Model
Home-page: https://github.com/mdrft/wildqat
Author: mdrft
Author-email: info@mdrft.com
License: Apache Software License
Download-URL: https://github.com/mdrft/wildqat_qdk/tarball/1.1.1
Platform: UNKNOWN
Classifier: Development Status :: 3 - Alpha
Classifier: Intended Audience :: Developers
Classifier: Programming Language :: Python :: 3
